{
  "$schema": "https://raw.githubusercontent.com/sims4toolkit/misc/main/json-schemas/docs-item-schema.json",
  "imports": [
    "import { TODO } from \"@s4tk/TODO\"; // ESM",
    "const { TODO } = require(\"@s4tk/TODO\"); // CJS"
  ],
  "header": {
    "title": {
      "name": "Example"
    },
    "description": "Lorem ipsum.",
    "sourceCode": "/src/example.ts"
  },
  "sections": [
    {
      "content": [
        {
          "displayType": "general",
          "paragraphs": []
        }
      ]
    }
  ]
}